speech_recognition_inference/__init__
speech_recognition_inference/cli.py
speech_recognition_inference/logger.py
speech_recognition_inference/utils.py
speech_recognition_inference/api/__init__.py
speech_recognition_inference/api/main.py
speech_recognition_inference/pipeline/__init__.py
speech_recognition_inference/pipeline/main.py
speech_recognition_inference-0.2.0.dist-info/METADATA
speech_recognition_inference-0.2.0.dist-info/WHEEL
speech_recognition_inference-0.2.0.dist-info/entry_points.txt
speech_recognition_inference-0.2.0.dist-info/RECORD
