Metadata-Version: 2.4
Name: speech-recognition-inference
Version: 0.2.0
Summary: A Speech-to-Text API.
Project-URL: Homepage, https://github.com/princeton-ddss/speech-recognition-inference
Author-email: "Junying (Alice) Fang" <jf3375@princeton.edu>, Colin Swaney <colinswaney@princeton.edu>
License-Expression: MIT
Classifier: License :: OSI Approved :: MIT License
Classifier: Operating System :: OS Independent
Classifier: Programming Language :: Python :: 3 :: Only
Classifier: Programming Language :: Python :: 3.11
Requires-Python: >=3.11
Requires-Dist: accelerate
Requires-Dist: colorlog>=6.9
Requires-Dist: datasets>=3.3.2
Requires-Dist: deprecated>=1.2.18
Requires-Dist: dotenv>=0.9.9
Requires-Dist: fastapi
Requires-Dist: ffmpeg>=1.4
Requires-Dist: huggingface-hub
Requires-Dist: librosa>=0.11
Requires-Dist: numpy<2
Requires-Dist: pydantic
Requires-Dist: pydub>=0.25.1
Requires-Dist: python-dotenv
Requires-Dist: slowapi
Requires-Dist: soundfile>0.12.0
Requires-Dist: torch>=2.6
Requires-Dist: transformers
Requires-Dist: typer>=0.15.2
Requires-Dist: uvicorn
